{
  "en": {
    "appTitle": "Modular Clicker",
    "appSubtitle": "Prototype",
    "footerHint": "Tip: this is a scaffold for expanding into a full clicker game.",

    "menuTitle": "Menu",
    "menuDescription": "Start a new game or continue. Adjust language, sound, and theme.",

    "newGame": "New Game",
    "continue": "Continue",

    "language": "Language",
    "sound": "Sound",
    "soundOn": "On",
    "soundOff": "Off",

    "theme": "Theme",
    "theme_light": "Light",
    "theme_dark": "Dark",
    "theme_forest": "Forest",
    "theme_space": "Space",
    "theme_frosty": "Frosty",

    "menuButton": "Menu",
    "shopTitle": "Upgrades",
    "gemCount": "Gems",
    "gpsDisplay": "per second",
    "clickPower": "per click",
    "totalClicks": "clicks",
    "totalEarned": "earned",
    "exportSave": "Export Save",
    "importSave": "Import Save",
    "tabGems": "Gems",
    "tabWood": "Wood",
    "tabStone": "Stone",
    "tabGold": "Gold",
    "woodCount": "Wood",
    "stoneCount": "Stone",
    "goldCount": "Gold",
    "rpsDisplay": "/s",
    "upgrade_gemRock": "Gem Rock",
    "upgrade_gemMine": "Gem Mine",
    "upgrade_gemFactory": "Gem Factory",
    "upgrade_gemPortal": "Gem Portal",
    "upgrade_woodSapling": "Wood Sapling",
    "upgrade_woodForest": "Wood Forest",
    "upgrade_woodMill": "Lumber Mill",
    "upgrade_woodGrove": "Enchanted Grove",
    "upgrade_stonePebbles": "Stone Pebbles",
    "upgrade_stoneQuarry": "Stone Quarry",
    "upgrade_stoneCrusher": "Stone Crusher",
    "upgrade_stoneMountain": "Living Mountain",
    "upgrade_goldNugget": "Gold Nugget",
    "upgrade_goldPan": "Gold Pan",
    "upgrade_goldMine": "Gold Mine",
    "upgrade_goldForge": "Golden Forge"
  },
  "es": {
    "appTitle": "Clicker Modular",
    "appSubtitle": "Prototipo",
    "footerHint": "Consejo: esto es una base para ampliar a un clicker completo.",

    "menuTitle": "Menú",
    "menuDescription": "Inicia una nueva partida o continúa. Ajusta idioma, sonido y tema.",

    "newGame": "Nueva partida",
    "continue": "Continuar",

    "language": "Idioma",
    "sound": "Sonido",
    "soundOn": "Activado",
    "soundOff": "Desactivado",

    "theme": "Tema",
    "theme_light": "Claro",
    "theme_dark": "Oscuro",
    "theme_forest": "Bosque",
    "theme_space": "Espacio",
    "theme_frosty": "Helado",

    "menuButton": "Menú",
    "shopTitle": "Mejoras",
    "gemCount": "Gemas",
    "gpsDisplay": "por segundo",
    "clickPower": "por clic",
    "totalClicks": "clics",
    "totalEarned": "ganado",
    "exportSave": "Exportar guardado",
    "importSave": "Importar guardado",
    "tabGems": "Gemas",
    "tabWood": "Madera",
    "tabStone": "Piedra",
    "tabGold": "Oro",
    "woodCount": "Madera",
    "stoneCount": "Piedra",
    "goldCount": "Oro",
    "rpsDisplay": "/s",
    "upgrade_gemRock": "Roca de Gemas",
    "upgrade_gemMine": "Mina de Gemas",
    "upgrade_gemFactory": "Fábrica de Gemas",
    "upgrade_gemPortal": "Portal de Gemas",
    "upgrade_woodSapling": "Brote de Madera",
    "upgrade_woodForest": "Bosque de Madera",
    "upgrade_woodMill": "Aserradero",
    "upgrade_woodGrove": "Arboleda Encantada",
    "upgrade_stonePebbles": "Guijarros de Piedra",
    "upgrade_stoneQuarry": "Cantera de Piedra",
    "upgrade_stoneCrusher": "Trituradora de Piedra",
    "upgrade_stoneMountain": "Montaña Viva",
    "upgrade_goldNugget": "Pepita de Oro",
    "upgrade_goldPan": "Batea de Oro",
    "upgrade_goldMine": "Mina de Oro",
    "upgrade_goldForge": "Forja Dorada"
  },
  "de": {
    "appTitle": "Modularer Clicker",
    "appSubtitle": "Prototyp",
    "footerHint": "Tipp: Dies ist ein Gerüst zum Ausbau zu einem vollständigen Clicker-Spiel.",

    "menuTitle": "Menü",
    "menuDescription": "Starte ein neues Spiel oder setze fort. Sprache, Sound und Theme anpassen.",

    "newGame": "Neues Spiel",
    "continue": "Fortsetzen",

    "language": "Sprache",
    "sound": "Sound",
    "soundOn": "An",
    "soundOff": "Aus",

    "theme": "Theme",
    "theme_light": "Hell",
    "theme_dark": "Dunkel",
    "theme_forest": "Wald",
    "theme_space": "Weltraum",
    "theme_frosty": "Frostig",

    "menuButton": "Menü",
    "shopTitle": "Upgrades",
    "gemCount": "Edelsteine",
    "gpsDisplay": "pro Sekunde",
    "clickPower": "pro Klick",
    "totalClicks": "Klicks",
    "totalEarned": "verdient",
    "exportSave": "Speichern exportieren",
    "importSave": "Speichern importieren",
    "tabGems": "Edelsteine",
    "tabWood": "Holz",
    "tabStone": "Stein",
    "tabGold": "Gold",
    "woodCount": "Holz",
    "stoneCount": "Stein",
    "goldCount": "Gold",
    "rpsDisplay": "/s",
    "upgrade_gemRock": "Edelstein-Felsen",
    "upgrade_gemMine": "Edelstein-Mine",
    "upgrade_gemFactory": "Edelstein-Fabrik",
    "upgrade_gemPortal": "Edelstein-Portal",
    "upgrade_woodSapling": "Holz-Setzling",
    "upgrade_woodForest": "Holz-Wald",
    "upgrade_woodMill": "Sägewerk",
    "upgrade_woodGrove": "Verzauberter Hain",
    "upgrade_stonePebbles": "Stein-Kiesel",
    "upgrade_stoneQuarry": "Steinbruch",
    "upgrade_stoneCrusher": "Steinbrecher",
    "upgrade_stoneMountain": "Lebender Berg",
    "upgrade_goldNugget": "Gold-Nugget",
    "upgrade_goldPan": "Goldpfanne",
    "upgrade_goldMine": "Gold-Mine",
    "upgrade_goldForge": "Goldene Schmiede"
  },
  "it": {
    "appTitle": "Clicker Modulare",
    "appSubtitle": "Prototipo",
    "footerHint": "Suggerimento: questa è una base per espandere in un vero clicker.",

    "menuTitle": "Menu",
    "menuDescription": "Avvia una nuova partita o continua. Modifica lingua, suono e tema.",

    "newGame": "Nuova partita",
    "continue": "Continua",

    "language": "Lingua",
    "sound": "Suono",
    "soundOn": "On",
    "soundOff": "Off",

    "theme": "Tema",
    "theme_light": "Chiaro",
    "theme_dark": "Scuro",
    "theme_forest": "Foresta",
    "theme_space": "Spazio",
    "theme_frosty": "Ghiacciato",

    "menuButton": "Menu",
    "shopTitle": "Miglioramenti",
    "gemCount": "Gemme",
    "gpsDisplay": "al secondo",
    "clickPower": "per clic",
    "totalClicks": "clic",
    "totalEarned": "guadagnato",
    "exportSave": "Esporta salvataggio",
    "importSave": "Importa salvataggio",
    "tabGems": "Gemme",
    "tabWood": "Legno",
    "tabStone": "Pietra",
    "tabGold": "Oro",
    "woodCount": "Legno",
    "stoneCount": "Pietra",
    "goldCount": "Oro",
    "rpsDisplay": "/s",
    "upgrade_gemRock": "Roccia di Gemme",
    "upgrade_gemMine": "Miniera di Gemme",
    "upgrade_gemFactory": "Fabbrica di Gemme",
    "upgrade_gemPortal": "Portale di Gemme",
    "upgrade_woodSapling": "Arboscello di Legno",
    "upgrade_woodForest": "Foresta di Legno",
    "upgrade_woodMill": "Segheria",
    "upgrade_woodGrove": "Bosco Incantato",
    "upgrade_stonePebbles": "Ciottoli di Pietra",
    "upgrade_stoneQuarry": "Cava di Pietra",
    "upgrade_stoneCrusher": "Frantumatore di Pietra",
    "upgrade_stoneMountain": "Montagna Vivente",
    "upgrade_goldNugget": "Pepita d'Oro",
    "upgrade_goldPan": "Padella d'Oro",
    "upgrade_goldMine": "Miniera d'Oro",
    "upgrade_goldForge": "Forgia Dorata"
  },
  "fr": {
    "appTitle": "Clicker Modulaire",
    "appSubtitle": "Prototype",
    "footerHint": "Astuce : ceci est une base pour étendre vers un vrai clicker.",

    "menuTitle": "Menu",
    "menuDescription": "Démarre une nouvelle partie ou continue. Ajuste langue, son et thème.",

    "newGame": "Nouvelle partie",
    "continue": "Continuer",

    "language": "Langue",
    "sound": "Son",
    "soundOn": "Activé",
    "soundOff": "Désactivé",

    "theme": "Thème",
    "theme_light": "Clair",
    "theme_dark": "Sombre",
    "theme_forest": "Forêt",
    "theme_space": "Espace",
    "theme_frosty": "Givré",

    "menuButton": "Menu",
    "shopTitle": "Améliorations",
    "gemCount": "Gemmes",
    "gpsDisplay": "par seconde",
    "clickPower": "par clic",
    "totalClicks": "clics",
    "totalEarned": "gagné",
    "exportSave": "Exporter sauvegarde",
    "importSave": "Importer sauvegarde",
    "tabGems": "Gemmes",
    "tabWood": "Bois",
    "tabStone": "Pierre",
    "tabGold": "Or",
    "woodCount": "Bois",
    "stoneCount": "Pierre",
    "goldCount": "Or",
    "rpsDisplay": "/s",
    "upgrade_gemRock": "Roche de Gemmes",
    "upgrade_gemMine": "Mine de Gemmes",
    "upgrade_gemFactory": "Usine de Gemmes",
    "upgrade_gemPortal": "Portail de Gemmes",
    "upgrade_woodSapling": "Pousse de Bois",
    "upgrade_woodForest": "Forêt de Bois",
    "upgrade_woodMill": "Scierie",
    "upgrade_woodGrove": "Bosquet Enchanté",
    "upgrade_stonePebbles": "Galets de Pierre",
    "upgrade_stoneQuarry": "Carrière de Pierre",
    "upgrade_stoneCrusher": "Broyeur de Pierre",
    "upgrade_stoneMountain": "Montagne Vivante",
    "upgrade_goldNugget": "Pépite d'Or",
    "upgrade_goldPan": "Batée d'Or",
    "upgrade_goldMine": "Mine d'Or",
    "upgrade_goldForge": "Forge Dorée"
  },
  "pt": {
    "appTitle": "Clicker Modular",
    "appSubtitle": "Protótipo",
    "footerHint": "Dica: isto é uma base para expandir para um clicker completo.",

    "menuTitle": "Menu",
    "menuDescription": "Comece um novo jogo ou continue. Ajuste idioma, som e tema.",

    "newGame": "Novo jogo",
    "continue": "Continuar",

    "language": "Idioma",
    "sound": "Som",
    "soundOn": "Ligado",
    "soundOff": "Desligado",

    "theme": "Tema",
    "theme_light": "Claro",
    "theme_dark": "Escuro",
    "theme_forest": "Floresta",
    "theme_space": "Espaço",
    "theme_frosty": "Gelado",

    "menuButton": "Menu",
    "shopTitle": "Melhorias",
    "gemCount": "Gemas",
    "gpsDisplay": "por segundo",
    "clickPower": "por clique",
    "totalClicks": "cliques",
    "totalEarned": "ganho",
    "exportSave": "Exportar jogo",
    "importSave": "Importar jogo",
    "tabGems": "Gemas",
    "tabWood": "Madeira",
    "tabStone": "Pedra",
    "tabGold": "Ouro",
    "woodCount": "Madeira",
    "stoneCount": "Pedra",
    "goldCount": "Ouro",
    "rpsDisplay": "/s",
    "upgrade_gemRock": "Rocha de Gemas",
    "upgrade_gemMine": "Mina de Gemas",
    "upgrade_gemFactory": "Fábrica de Gemas",
    "upgrade_gemPortal": "Portal de Gemas",
    "upgrade_woodSapling": "Muda de Madeira",
    "upgrade_woodForest": "Floresta de Madeira",
    "upgrade_woodMill": "Serraria",
    "upgrade_woodGrove": "Bosque Encantado",
    "upgrade_stonePebbles": "Seixos de Pedra",
    "upgrade_stoneQuarry": "Pedreira",
    "upgrade_stoneCrusher": "Triturador de Pedra",
    "upgrade_stoneMountain": "Montanha Viva",
    "upgrade_goldNugget": "Pepita de Ouro",
    "upgrade_goldPan": "Bateia de Ouro",
    "upgrade_goldMine": "Mina de Ouro",
    "upgrade_goldForge": "Forja Dourada"
  }
}
